kubernetes_mcp_server/__init__.py
kubernetes_mcp_server/__main__.py
kubernetes_mcp_server/kubernetes_mcp_server.py
kubernetes_mcp_server-0.0.56.dist-info/METADATA
kubernetes_mcp_server-0.0.56.dist-info/WHEEL
kubernetes_mcp_server-0.0.56.dist-info/entry_points.txt
kubernetes_mcp_server-0.0.56.dist-info/top_level.txt
kubernetes_mcp_server-0.0.56.dist-info/RECORD
