Metadata-Version: 2.4
Name: kubernetes-mcp-server
Version: 0.0.56
Summary: Kubernetes MCP Server (Model Context Protocol) with special support for OpenShift
Author-email: Marc Nuri <marc@marcnuri.com>
License-Expression: Apache-2.0
Project-URL: Homepage, https://github.com/containers/kubernetes-mcp-server
Project-URL: Repository, https://github.com/containers/kubernetes-mcp-server
Classifier: Programming Language :: Python :: 3
Classifier: Operating System :: OS Independent
Requires-Python: >=3.6
